rightnow/__init__.py
rightnow/time.py
rightnow-1.0.2.dist-info/METADATA
rightnow-1.0.2.dist-info/WHEEL
rightnow-1.0.2.dist-info/top_level.txt
rightnow-1.0.2.dist-info/RECORD
