Metadata-Version: 2.1
Name: rightnow
Version: 1.0.2
Summary: Default template for PDM package
Author-email: j25ng <jsan2861@gmail.com>
License: MIT
Requires-Python: >=3.11
Requires-Dist: pytz>=2024.2
